galtea/__init__.py
galtea/connection/__init__.py
galtea/connection/sdk_connection.py
galtea/datasets/__init__.py
galtea/datasets/dataset_manager.py
galtea/models/__init__.py
galtea/models/base_fields.py
galtea/models/template_fields.py
galtea/models/user.py
galtea/templates/__init__.py
galtea/templates/concrete.py
galtea/templates/creator.py
galtea/templates/simple_ab_testing.py
galtea/templates/template.py
galtea/users/__init__.py
galtea/users/html_email_template.py
galtea/users/user_mail_notifier.py
galtea/users/user_manager.py
galtea/utils.py
galtea/workspaces/__init__.py
galtea/workspaces/workspace_manager.py
galtea_sdk-0.1.4.dist-info/METADATA
galtea_sdk-0.1.4.dist-info/WHEEL
galtea_sdk-0.1.4.dist-info/RECORD
