Metadata-Version: 2.1
Name: galtea-sdk
Version: 0.1.4
Summary: 
Author: Nicola Massarenti
Requires-Python: >=3.9,<3.13
Classifier: Programming Language :: Python :: 3
Classifier: Programming Language :: Python :: 3.9
Classifier: Programming Language :: Python :: 3.10
Classifier: Programming Language :: Python :: 3.11
Classifier: Programming Language :: Python :: 3.12
Requires-Dist: argilla (==2.4.0)
Requires-Dist: email-validator (==2.1.2)
Requires-Dist: pydantic (>=2.9.2,<3.0.0)
Requires-Dist: python-dotenv (>=1.0.1,<2.0.0)
